api.py
baml_client/__init__.py
baml_client/async_client.py
baml_client/globals.py
baml_client/inlinedbaml.py
baml_client/partial_types.py
baml_client/sync_client.py
baml_client/tracing.py
baml_client/type_builder.py
baml_client/types.py
ii_researcher/__init__.py
ii_researcher/cli.py
ii_researcher/config.py
ii_researcher/events.py
ii_researcher/pipeline/__init__.py
ii_researcher/pipeline/agent.py
ii_researcher/pipeline/evaluator.py
ii_researcher/pipeline/schemas.py
ii_researcher/pipeline/state.py
ii_researcher/pipeline/action_handler/__init__.py
ii_researcher/pipeline/action_handler/answer.py
ii_researcher/pipeline/action_handler/base.py
ii_researcher/pipeline/action_handler/reflect.py
ii_researcher/pipeline/action_handler/search.py
ii_researcher/pipeline/action_handler/visit.py
ii_researcher/reasoning/__init__.py
ii_researcher/reasoning/agent.py
ii_researcher/reasoning/config.py
ii_researcher/reasoning/utils.py
ii_researcher/reasoning/clients/__init__.py
ii_researcher/reasoning/clients/openai_client.py
ii_researcher/reasoning/clients/report.py
ii_researcher/reasoning/models/__init__.py
ii_researcher/reasoning/models/action.py
ii_researcher/reasoning/models/output.py
ii_researcher/reasoning/models/trace.py
ii_researcher/reasoning/tools/__init__.py
ii_researcher/reasoning/tools/base.py
ii_researcher/reasoning/tools/registry.py
ii_researcher/reasoning/tools/tool_history.py
ii_researcher/reasoning/tools/web_scraper.py
ii_researcher/reasoning/tools/web_search.py
ii_researcher/tools/__init__.py
ii_researcher/tools/duck_search.py
ii_researcher/tools/read.py
ii_researcher/tools/web_scraper_compressor.py
ii_researcher/tools/compressor/__init__.py
ii_researcher/tools/compressor/base.py
ii_researcher/tools/compressor/context_compressor.py
ii_researcher/tools/compressor/embedding_compressor.py
ii_researcher/tools/compressor/llm_compressor.py
ii_researcher/tools/scraper/__init__.py
ii_researcher/tools/scraper/scraper.py
ii_researcher/tools/scraper/utils.py
ii_researcher_test-0.1.2.dist-info/licenses/LICENSE
ii_researcher_test-0.1.2.dist-info/METADATA
ii_researcher_test-0.1.2.dist-info/WHEEL
ii_researcher_test-0.1.2.dist-info/top_level.txt
ii_researcher_test-0.1.2.dist-info/RECORD
